KmerDecon/__init__.py
KmerDecon/bloom_filter.py
KmerDecon/build_data_structure.py
KmerDecon/cuckoofilter.py
KmerDecon/decontaminate_reads.py
KmerDecon/utils.py
KmerDecon-0.2.0.dist-info/LICENSE
KmerDecon-0.2.0.dist-info/METADATA
KmerDecon-0.2.0.dist-info/WHEEL
KmerDecon-0.2.0.dist-info/entry_points.txt
KmerDecon-0.2.0.dist-info/top_level.txt
KmerDecon-0.2.0.dist-info/RECORD
