Metadata-Version: 2.1
Name: KmerDecon
Version: 0.2.0
Summary: A fast, memory-efficient tool for decontaminating sequencing reads using Bloom filters.
Home-page: https://github.com/skysky2333/KmerDecon
Author: Yuxiang Li, Yujia Feng, Xiaoyi Chen
Classifier: Programming Language :: Python :: 3
Classifier: License :: OSI Approved :: MIT License
Classifier: Operating System :: OS Independent
Requires-Python: >=3.6
License-File: LICENSE
Requires-Dist: bitarray>=2.1.0
Requires-Dist: biopython>=1.78
Requires-Dist: mmh3>=2.5.1
Requires-Dist: hyperloglog>=0.0.12
Requires-Dist: tqdm>=4.8.0
